youtube/__init__.py
youtube/main.py
youtube/video_download.py
utube_video_download-0.0.7.dist-info/LICENSE.txt
utube_video_download-0.0.7.dist-info/METADATA
utube_video_download-0.0.7.dist-info/WHEEL
utube_video_download-0.0.7.dist-info/entry_points.txt
utube_video_download-0.0.7.dist-info/top_level.txt
utube_video_download-0.0.7.dist-info/RECORD
