Metadata-Version: 2.1
Name: utube-video-download
Version: 0.0.7
Summary: A tool for downloading single and playlist videos from youtube with a progress bar
Home-page: https://github.com/Pato546/youtube_video_downloader
Author: Pato
Author-email: boatengpato.pb@gmail.com
License: MIT
Platform: UNKNOWN
Classifier: Programming Language :: Python :: 3
Classifier: License :: OSI Approved :: MIT License
Classifier: Operating System :: Microsoft :: Windows
Requires-Python: >=3.9
License-File: LICENSE.txt
Requires-Dist: pytube (>=11.0.2)
Requires-Dist: requests (==2.26.0)
Requires-Dist: rich (>=10.15.2)
Requires-Dist: emoji (==1.6.1)
Requires-Dist: tqdm (==4.62.3)
Requires-Dist: pyperclip (==1.8.2)
